jaxoplanet/__init__.py
jaxoplanet/constants.py
jaxoplanet/jaxoplanet_version.py
jaxoplanet/object_stack.py
jaxoplanet/proto.py
jaxoplanet/py.typed
jaxoplanet/test_utils.py
jaxoplanet/types.py
jaxoplanet/utils.py
jaxoplanet/core/__init__.py
jaxoplanet/core/kepler.py
jaxoplanet/core/limb_dark.py
jaxoplanet/experimental/__init__.py
jaxoplanet/experimental/limb_dark_poly_coeffs.py
jaxoplanet/light_curves/__init__.py
jaxoplanet/light_curves/emission.py
jaxoplanet/light_curves/limb_dark.py
jaxoplanet/light_curves/transforms.py
jaxoplanet/light_curves/types.py
jaxoplanet/light_curves/utils.py
jaxoplanet/orbits/__init__.py
jaxoplanet/orbits/keplerian.py
jaxoplanet/orbits/transit.py
jaxoplanet/orbits/ttv.py
jaxoplanet/starry/__init__.py
jaxoplanet/starry/doppler.py
jaxoplanet/starry/light_curves.py
jaxoplanet/starry/orbit.py
jaxoplanet/starry/surface.py
jaxoplanet/starry/system_observable.py
jaxoplanet/starry/utils.py
jaxoplanet/starry/visualization.py
jaxoplanet/starry/ylm.py
jaxoplanet/starry/core/basis.py
jaxoplanet/starry/core/polynomials.py
jaxoplanet/starry/core/rotation.py
jaxoplanet/starry/core/s2fft_rotation.py
jaxoplanet/starry/core/solution.py
jaxoplanet/starry/core/wigner3j.py
jaxoplanet/starry/multiprecision/__init__.py
jaxoplanet/starry/multiprecision/basis.py
jaxoplanet/starry/multiprecision/flux.py
jaxoplanet/starry/multiprecision/precision.py
jaxoplanet/starry/multiprecision/rotation.py
jaxoplanet/starry/multiprecision/solution.py
jaxoplanet/starry/multiprecision/utils.py
jaxoplanet-0.1.0.dist-info/METADATA
jaxoplanet-0.1.0.dist-info/WHEEL
jaxoplanet-0.1.0.dist-info/licenses/LICENSE
jaxoplanet-0.1.0.dist-info/RECORD
