Metadata-Version: 2.4
Name: jaxoplanet
Version: 0.1.0
Summary: Probabilistic models for exoplanet inference in JAX
Project-URL: Homepage, https://jax.exoplanet.codes
Project-URL: Source, https://github.com/exoplanet-dev/jaxoplanet
Project-URL: Bug Tracker, https://github.com/exoplanet-dev/jaxoplanet/issues
Author-email: Dan Foreman-Mackey <foreman.mackey@gmail.com>
License: MIT License
License-File: LICENSE
Classifier: Development Status :: 4 - Beta
Classifier: Intended Audience :: Developers
Classifier: Intended Audience :: Science/Research
Classifier: License :: OSI Approved :: MIT License
Classifier: Operating System :: OS Independent
Classifier: Programming Language :: Python
Classifier: Programming Language :: Python :: 3
Requires-Python: >=3.10
Requires-Dist: equinox
Requires-Dist: jax
Requires-Dist: jaxlib
Provides-Extra: comparison
Requires-Dist: numpy; extra == 'comparison'
Requires-Dist: starry; extra == 'comparison'
Requires-Dist: tqdm; extra == 'comparison'
Requires-Dist: xarray<2023.10.0; extra == 'comparison'
Provides-Extra: dev
Requires-Dist: astropy; extra == 'dev'
Requires-Dist: black; extra == 'dev'
Requires-Dist: gmpy2; extra == 'dev'
Requires-Dist: mpmath; extra == 'dev'
Requires-Dist: nox; extra == 'dev'
Requires-Dist: pre-commit; extra == 'dev'
Requires-Dist: pytest; extra == 'dev'
Requires-Dist: ruff; extra == 'dev'
Requires-Dist: sympy; extra == 'dev'
Provides-Extra: docs
Requires-Dist: arviz; extra == 'docs'
Requires-Dist: astropy; extra == 'docs'
Requires-Dist: corner; extra == 'docs'
Requires-Dist: ipywidgets; extra == 'docs'
Requires-Dist: jaxopt; extra == 'docs'
Requires-Dist: matplotlib; extra == 'docs'
Requires-Dist: myst-nb; extra == 'docs'
Requires-Dist: numpyro; extra == 'docs'
Requires-Dist: numpyro-ext; extra == 'docs'
Requires-Dist: sphinx-autoapi<3.2.0; extra == 'docs'
Requires-Dist: sphinx-book-theme; extra == 'docs'
Requires-Dist: sphinx-design; extra == 'docs'
Provides-Extra: test
Requires-Dist: batman-package; extra == 'test'
Requires-Dist: exoplanet-core; extra == 'test'
Requires-Dist: pytest; extra == 'test'
Requires-Dist: pytest-xdist; extra == 'test'
Provides-Extra: test-math
Requires-Dist: gmpy2; extra == 'test-math'
Requires-Dist: mpmath; extra == 'test-math'
